<?xml version="1.0"?>
<openerp>
    <data>

    <record model="ir.ui.view" id="purchase_order_tree_inherit">
        <field name="name">purchase.order.tree.inherit</field>
        <field name="type">tree</field>
        <field name="model">purchase.order</field>
        <field name="inherit_id" ref="purchase.purchase_order_tree"/>
        <field name="arch" type="xml">
            <field name="name" position="after">
                <field name="tender_id"/>
            </field>
        </field>
    </record>

    <record model="ir.ui.view" id="purchase_order_form_inherit">
        <field name="name">purchase.order.form.inherit</field>
        <field name="type">form</field>
        <field name="model">purchase.order</field>
        <field name="inherit_id" ref="purchase.purchase_order_form"/>
        <field name="arch" type="xml">
            <field name="partner_ref" position="after">
                <field name="tender_id" select="2"/>
            </field>
        </field>
    </record>

<!-- view for  purchase.tender  -->
        <record model="ir.ui.view" id="view_purchase_tender_form">
            <field name="name">purchase.tender.form</field>
            <field name="type">form</field>
            <field name="model">purchase.tender</field>
            <field name="arch" type="xml">
                <form string="Purchase Tender">
                    <field name="name" select="1"/>
                    <field name="description" select="2" colspan="4"/>
                    <separator string="Purchase Orders" colspan="4"/>
                    <field name="purchase_ids" nolabel="1" colspan="4">
                        <tree string="Purchase Order">
                            <field name="name"/>
                            <field name="date_order"/>
                            <field name="partner_id"/>
                            <field name="state"/>
                            <field name="notes"/>
                        </tree>
                    </field>
                </form>
            </field>
        </record>
        <record model="ir.ui.view" id="view_purchase_tender_tree">
            <field name="name">purchase.tender.tree</field>
            <field name="type">tree</field>
            <field name="model">purchase.tender</field>
            <field name="arch" type="xml">
                <tree string="Purchase Tender">
                    <field name="name"/>
                    <field name="description"/>
                </tree>
            </field>
        </record>
        <record model="ir.actions.act_window" id="action_purchase_tender">
            <field name="name">Purchase Tender</field>
            <field name="type">ir.actions.act_window</field>
            <field name="res_model">purchase.tender</field>
            <field name="view_type">form</field>
            <field name="view_id" ref="view_purchase_tender_tree"/>
        </record>
        <menuitem name="Purchase Tenders" id="menu_purchase_tender" parent="purchase.menu_purchase_root"/>
        <menuitem name="Purchase Tender" id="menu_purchase_Tender1" parent="menu_purchase_tender" action="action_purchase_tender"/>
    </data>
</openerp>
