<?xml version="1.0"?>
<openerp>
<data>

    <record model="ir.ui.view" id="view_commission_month_form">
        <field name="name">commission.month.form</field>
        <field name="model">report.commission.month</field>
        <field name="type">form</field>
        <field name="arch" type="xml">
            <form string="sales agent commission">
                <field name="name" select="1"/>
                <field name="sono" select="1"/>
                <field name="productname" select="1"/>
                <field name="product_quantity" select="1"/>
                <field name="invno" select="1"/>
                <field name="in_date"/>
                <field name="inv_total" select="1"/>
                <field name="state"/>
                <field name="comrate" select="1"/>
                <field name="commission" select="1"/>
                <field name="pdate"/>
            </form>
        </field>
    </record>


    <record model="ir.ui.view" id="view_commission_month_tree">
        <field name="name">commission.month.form.tree</field>
        <field name="model">report.commission.month</field>
        <field name="type">tree</field>
        <field name="arch" type="xml">
            <tree string="sales agent commission">

                <field name="name" select="1"/>
                <field name="sono" select="1"/>
                <field name="productname" select="1"/>
                <field name="product_quantity" select="1"/>
                <field name="invno" select="1"/>
                <field name="in_date"/>
                <field name="inv_total" select="1"/>
                <field name="state"/>
                <field name="comrate" select="1"/>
                <field name="commission" select="1"/>
                <field name="pdate"/>
                </tree>
        </field>
    </record>
    <record model="ir.actions.act_window" id="action_sales agent commission_tree_month">
        <field name="name">commission.month.form.tree</field>
        <field name="res_model">report.commission.month</field>
        <field name="view_type">form</field>
        <field name="view_mode">tree</field>
        <field name="domain">[('in_date','like',time.strftime('%Y-%m'))]</field>
    </record>
    
    <menuitem name="Reporting" id="menu_sale_commisions_reporting" parent="sale.menu_sale_root"/>
    <menuitem name="This Month" id="menu_sale_commisions_reporting_this" parent="menu_sale_commisions_reporting"/>
    <menuitem name="Commissions of This Month" id="menu_sale_commisions_reporting_this_of_commision" parent="menu_sale_commisions_reporting_this" action="action_sales agent commission_tree_month"/>
    
    <record model="ir.ui.view" id="view_commission_all_form">
        <field name="name">commission.all.form</field>
        <field name="model">report.commission.month</field>
        <field name="type">form</field>
        <field name="arch" type="xml">
            <form string="sales agent all commission">
                <field name="name" select="1"/>
                <field name="sono" select="1"/>
                <field name="productname" select="1"/>
                <field name="product_quantity" select="1"/>
                <field name="invno" select="1"/>
                <field name="in_date"/>
                <field name="inv_total" select="1"/>
                <field name="state"/>
                <field name="comrate" select="1"/>
                <field name="commission" select="1"/>
                <field name="pdate"/>
            </form>
        </field>
    </record>

    <record model="ir.ui.view" id="view_commission_all_tree">
        <field name="name">commission.all.form.tree</field>
        <field name="model">report.commission.month</field>
        <field name="type">tree</field>
        <field name="arch" type="xml">
            <tree string="sales agent all commission">

                <field name="name" select="1"/>
                <field name="sono" select="1"/>
                <field name="productname" select="1"/>
                <field name="product_quantity" select="1"/>
                <field name="invno" select="1"/>
                <field name="in_date"/>
                <field name="inv_total" select="1"/>
                <field name="state"/>
                <field name="comrate" select="1"/>
                <field name="commission" select="1"/>
                <field name="pdate"/>
                </tree>
        </field>
    </record>
    <record model="ir.actions.act_window" id="action_sales agent commission_tree_all">
        <field name="name">commission.all.form.tree</field>
        <field name="res_model">report.commission.month</field>
        <field name="view_type">form</field>
        <field name="view_mode">tree</field>
    </record>
    <menuitem name="All Commissions" id="menu_sale_commisions_reporting_all_com" parent="menu_sale_commisions_reporting"/>
    <menuitem name="Commissions" id="menu_sale_commisions_reporting_all_of_commision" parent="menu_sale_commisions_reporting_all_com" action="action_sales agent commission_tree_all"/>
    
</data>
</openerp>
